salutator/__init__.py
salutator/_version.py
salutator/animals/__init__.py
salutator/animals/goodbyes.py
salutator/animals/greetings.py
salutator/eso/__init__.py
salutator/eso/core.py
salutator/eso/utils.py
salutator/eso/tables/__init__.py
salutator/eso/tables/eso_table.py
salutator/eso/tables/namespace.py
salutator/eso/tables/obs_core.py
salutator/eso/tests/__init__.py
salutator/eso/tests/setup_package.py
salutator/eso/tests/test_eso.py
salutator/eso/tests/test_eso_remote.py
salutator/humans/__init__.py
salutator/humans/goodbyes.py
salutator/humans/greetings.py
salutator/minerals/__init__.py
salutator/minerals/goodbyes.py
salutator/minerals/greetings.py
salutator/plants/__init__.py
salutator/plants/goodbyes.py
salutator/plants/greetings.py
tests/__init__.py
tests/test_salutator.py
salutator-0.9.922.dist-info/METADATA
salutator-0.9.922.dist-info/WHEEL
salutator-0.9.922.dist-info/top_level.txt
salutator-0.9.922.dist-info/RECORD
