Metadata-Version: 2.4
Name: salutator
Version: 0.9.922
Summary: A simple package for greetings and goodbyes
Home-page: https://github.com/juanmcloaiza/salutator
Author: John Doe
Author-email: john@doe.com
License: BSD
Classifier: Programming Language :: Python :: 3
Classifier: Operating System :: OS Independent
Requires-Python: >=3.7
Requires-Dist: numpy>=1.24
Requires-Dist: pandas>=2.0
Requires-Dist: requests>=2.30
Requires-Dist: matplotlib>=3.7
Requires-Dist: astropy
Requires-Dist: bs4
Requires-Dist: pyvo
Requires-Dist: astroquery
Requires-Dist: openai
Provides-Extra: dev
Requires-Dist: pytest>=7.4; extra == "dev"
Requires-Dist: pytest-doctestplus>=1.4; extra == "dev"
Requires-Dist: pytest-timeout; extra == "dev"
Requires-Dist: pytest-astropy; extra == "dev"
Requires-Dist: matplotlib; extra == "dev"
Requires-Dist: pytest-dependency; extra == "dev"
Requires-Dist: pytest-rerunfailures; extra == "dev"
Requires-Dist: fsspec[http]; extra == "dev"
Requires-Dist: moto[s3]; extra == "dev"
